setup.cfg
setup.py
smallcli/__init__.py
smallcli/main.py
smallcli/utils.py
smallcli.egg-info/PKG-INFO
smallcli.egg-info/SOURCES.txt
smallcli.egg-info/dependency_links.txt
smallcli.egg-info/requires.txt
smallcli.egg-info/top_level.txt
smallcli/commands/__init__.py
smallcli/commands/base.py
smallcli/commands/generic.py
smallcli/commands1/__init__.py
smallcli/commands1/generic.py
smallcli/libs/__init__.py
smallcli/libs/cmdmanager.py
smallcli/libs/shell.py
smallcli/libs/style.py
smallcli/resources/__init__.py
smallcli/resources/ssh.py