Metadata-Version: 1.1
Name: smallcli
Version: 0.1
Summary: CLI framework for automation scripts
Home-page: https://github.com/knetsolutions/smallcli
Author: S.Suresh Kumar
Author-email: sureshkumarr.s@gmail.com
License: Apache
Keywords: cli
Platform: UNKNOWN
Classifier: Development Status :: 5 - Production/Stable
Classifier: Intended Audience :: Developers
Classifier: Topic :: Software Development :: User Interfaces
Classifier: License :: OSI Approved :: MIT License
Classifier: Programming Language :: Python :: 2.7
